odoo/addons/mail_environment_office365/README.rst
odoo/addons/mail_environment_office365/__init__.py
odoo/addons/mail_environment_office365/__manifest__.py
odoo/addons/mail_environment_office365/i18n/it.po
odoo/addons/mail_environment_office365/i18n/mail_environment_office365.pot
odoo/addons/mail_environment_office365/models/__init__.py
odoo/addons/mail_environment_office365/models/fetchmail_server.py
odoo/addons/mail_environment_office365/models/ir_mail_server.py
odoo/addons/mail_environment_office365/readme/CONFIGURE.rst
odoo/addons/mail_environment_office365/readme/CONTRIBUTORS.rst
odoo/addons/mail_environment_office365/readme/DESCRIPTION.rst
odoo/addons/mail_environment_office365/static/description/icon.png
odoo/addons/mail_environment_office365/static/description/index.html
odoo14_addon_mail_environment_office365-14.0.1.0.1.dev8.dist-info/METADATA
odoo14_addon_mail_environment_office365-14.0.1.0.1.dev8.dist-info/WHEEL
odoo14_addon_mail_environment_office365-14.0.1.0.1.dev8.dist-info/top_level.txt
odoo14_addon_mail_environment_office365-14.0.1.0.1.dev8.dist-info/RECORD
